tk_box/__init__.py
tk_box-0.0.1.20220225.dist-info/METADATA
tk_box-0.0.1.20220225.dist-info/WHEEL
tk_box-0.0.1.20220225.dist-info/top_level.txt
tk_box-0.0.1.20220225.dist-info/RECORD
